dist/pyremotechrome-0.1.3-py3-none-any.whl
dist/pyremotechrome-0.1.3.tar.gz
dist/pyremotechrome-0.1.4-py3-none-any.whl
dist/pyremotechrome-0.1.4.tar.gz
pyremotechrome/__init__.py
pyremotechrome/__main__.py
pyremotechrome/util.py
pyremotechrome/config/__init__.py
pyremotechrome/config/config.py
pyremotechrome/server/__init__.py
pyremotechrome/server/favicon.ico
pyremotechrome/server/manager.py
pyremotechrome/server/server.py
pyremotechrome/session/__init__.py
pyremotechrome/session/base.py
pyremotechrome/session/mega.py
pyremotechrome/session/monitor/__init__.py
pyremotechrome/session/monitor/audio.py
pyremotechrome/session/monitor/display.py
pyremotechrome/session/support/common/__init__.py
pyremotechrome/session/support/common/directory.py
pyremotechrome/session/support/common/info.py
pyremotechrome/session/support/common/result.py
pyremotechrome/session/support/common/vector.py
pyremotechrome/session/support/options/__init__.py
pyremotechrome/session/support/options/ffmpeg.py
pyremotechrome-0.1.5.dist-info/LICENSE
pyremotechrome-0.1.5.dist-info/METADATA
pyremotechrome-0.1.5.dist-info/WHEEL
pyremotechrome-0.1.5.dist-info/top_level.txt
pyremotechrome-0.1.5.dist-info/RECORD
