Metadata-Version: 2.1
Name: pyremotechrome
Version: 0.1.5
Summary: PyRemoteChrome
Author-email: Wes-KW <dotdotdashdash2024@hotmail.com>
Project-URL: Homepage, https://github.com/Wes-KW/PyRemoteChrome
Project-URL: Issues, https://github.com/Wes-KW/PyRemoteChrome/issues
Classifier: Programming Language :: Python :: 3
Classifier: Programming Language :: Python :: 3.8
Classifier: Programming Language :: Python :: 3.9
Classifier: Programming Language :: Python :: 3.10
Classifier: Programming Language :: Python :: 3.11
Classifier: License :: OSI Approved :: MIT License
Classifier: Operating System :: POSIX :: Linux
Requires-Python: <4,>=3.8
License-File: LICENSE
Requires-Dist: selenium >=4.19.0
Requires-Dist: psutil >=5.9.8
Requires-Dist: PyVirtualDisplay >=3.0
Requires-Dist: requests >=2.32.1
Requires-Dist: pytz >=2024.1
